{"cameraMode":{"drawMode":0,"name":"Shaded","section":"Shading Mode"},"sceneLighting":false,"audioPlay":false,"sceneViewState":{"showFog":true,"showMaterialUpdate":false,"showSkybox":false,"showFlares":true,"showImageEffects":true,"showParticleSystems":true},"in2DMode":false,"pivot":{"x":-0.47259098291397097,"y":0.5336945652961731,"z":0.6539283394813538},"rotation":{"x":-0.3736170530319214,"y":0.15819017589092256,"z":-0.06469672173261643,"w":-0.9119726419448853},"size":0.6640604734420776,"orthographic":false}